advection/__init__.py
advection/advect_detect.py
advection/advection.py
advection-0.1.0.dist-info/licenses/AUTHORS.rst
advection-0.1.0.dist-info/licenses/LICENSE
advection-0.1.0.dist-info/METADATA
advection-0.1.0.dist-info/WHEEL
advection-0.1.0.dist-info/top_level.txt
advection-0.1.0.dist-info/RECORD
